CSA_S16/CSA_S16.py
CSA_S16/__init__.py
CSA_S16_python-0.1.2.dist-info/METADATA
CSA_S16_python-0.1.2.dist-info/WHEEL
CSA_S16_python-0.1.2.dist-info/top_level.txt
CSA_S16_python-0.1.2.dist-info/RECORD
