Metadata-Version: 2.1
Name: CSA-S16-python
Version: 0.1.2
Summary: Steel design equations based on CSA S16.
Home-page: https://github.com/samrich98/CSA_S16_python.git
Author: Sam Richardson
Author-email: sam.richardson@mai.utoronto.ca
Classifier: Programming Language :: Python :: 3
Classifier: License :: OSI Approved :: MIT License
Requires-Python: >=3.7
Requires-Dist: handcalcs
Requires-Dist: forallpeople
Requires-Dist: IPython
